{
  "filters": {
    "serviceId": "bbc_radio_one"
  },
  "service": {
    "id": "bbc_radio_one",
    "name": "BBC Radio 1",
    "type": "National Radio",
    "mediaType": "Audio",
    "scheduleUpdated": "2021-05-20T03:33:07.729Z"
  },
  "items": [
    {
      "id": "p09g7f2c",
      "service": {
        "id": "bbc_radio_one"
      },
      "version": {
        "id": "m000w4lt"
      },
      "episode": {
        "id": "m000w4lv",
        "title": "With Mara TK"
      },
      "brand": {
        "title": "Benji B"
      },
      "masterbrand": {
        "id": "bbc_radio_one"
      },
      "published_time": {
        "start": "2021-05-19T23:00:00.000Z",
        "end": "2021-05-20T01:00:00.000Z"
      }
    },
    {
      "id": "p09g7f2d",
      "service": {
        "id": "bbc_radio_one"
      },
      "version": {
        "id": "m000w52n"
      },
      "episode": {
        "id": "m000w52p",
        "title": "Lauren Mayberry (Chvrches) on arriving at the band they want to be"
      },
      "brand": {
        "title": "The Radio 1 Interview"
      },
      "masterbrand": {
        "id": "bbc_radio_one"
      },
      "published_time": {
        "start": "2021-05-20T01:00:00.000Z",
        "end": "2021-05-20T01:16:00.000Z"
      }
    },
    {
      "id": "p09g7f2f",
      "service": {
        "id": "bbc_radio_one"
      },
      "version": {
        "id": "m000w52q"
      },
      "episode": {
        "id": "m000w52r",
        "title": "20/05/2021"
      },
      "brand": {
        "title": "Radio 1 Playlists"
      },
      "masterbrand": {
        "id": "bbc_radio_one"
      },
      "published_time": {
        "start": "2021-05-20T01:16:00.000Z",
        "end": "2021-05-20T01:30:00.000Z"
      }
    },
    {
      "id": "p09g7f2g",
      "service": {
        "id": "bbc_radio_one"
      },
      "version": {
        "id": "m000sgnn"
      },
      "episode": {
        "id": "m000sgnp",
        "title": "Lucy Rose Chill Mix"
      },
      "brand": {
        "title": "Radio 1's Chill Mix"
      },
      "masterbrand": {
        "id": "bbc_radio_one"
      },
      "published_time": {
        "start": "2021-05-20T01:30:00.000Z",
        "end": "2021-05-20T02:00:00.000Z"
      }
    },
    {
      "id": "p09g7f2j",
      "service": {
        "id": "bbc_radio_one"
      },
      "version": {
        "id": "m000w52s"
      },
      "episode": {
        "id": "m000w52t",
        "title": "Listen to an hour of giant festival bangers"
      },
      "brand": {
        "title": "Radio 1's Festival Anthems"
      },
      "masterbrand": {
        "id": "bbc_radio_one"
      },
      "published_time": {
        "start": "2021-05-20T02:00:00.000Z",
        "end": "2021-05-20T03:00:00.000Z"
      }
    },
    {
      "id": "p09g7f2k",
      "service": {
        "id": "bbc_radio_one"
      },
      "version": {
        "id": "m000w52v"
      },
      "episode": {
        "id": "m000w52w",
        "title": "24/7 Dance..."
      },
      "brand": {
        "title": "Radio 1 Dance"
      },
      "masterbrand": {
        "id": "bbc_radio_one"
      },
      "published_time": {
        "start": "2021-05-20T03:00:00.000Z",
        "end": "2021-05-20T04:00:00.000Z"
      }
    },
    {
      "id": "p09g7f2l",
      "service": {
        "id": "bbc_radio_one"
      },
      "version": {
        "id": "m000w52x"
      },
      "episode": {
        "id": "m000w52y",
        "title": "with Arielle Free"
      },
      "brand": {
        "title": "Radio 1 Early Breakfast"
      },
      "masterbrand": {
        "id": "bbc_radio_one"
      },
      "published_time": {
        "start": "2021-05-20T04:00:00.000Z",
        "end": "2021-05-20T06:00:00.000Z"
      }
    },
    {
      "id": "p09g7f6k",
      "service": {
        "id": "bbc_radio_one"
      },
      "version": {
        "id": "m000w53y"
      },
      "episode": {
        "id": "m000w53z",
        "title": "Matt and Mollie are in for Greg"
      },
      "brand": {
        "title": "Radio 1 Breakfast with Greg James"
      },
      "masterbrand": {
        "id": "bbc_radio_one"
      },
      "published_time": {
        "start": "2021-05-20T06:00:00.000Z",
        "end": "2021-05-20T09:32:00.000Z"
      }
    },
    {
      "id": "p09g7f6l",
      "service": {
        "id": "bbc_radio_one"
      },
      "version": {
        "id": "m000w540"
      },
      "episode": {
        "id": "m000w541",
        "title": "20/05/2021"
      },
      "brand": {
        "title": "Clara Amfo"
      },
      "masterbrand": {
        "id": "bbc_radio_one"
      },
      "published_time": {
        "start": "2021-05-20T09:32:00.000Z",
        "end": "2021-05-20T11:45:00.000Z"
      }
    },
    {
      "id": "p09g7f6m",
      "service": {
        "id": "bbc_radio_one"
      },
      "version": {
        "id": "m000w542"
      },
      "episode": {
        "id": "m000w543",
        "title": "20/05/2021"
      },
      "brand": {
        "title": "Newsbeat"
      },
      "masterbrand": {
        "id": "bbc_radio_one"
      },
      "published_time": {
        "start": "2021-05-20T11:45:00.000Z",
        "end": "2021-05-20T12:00:00.000Z"
      }
    },
    {
      "id": "p09g7f6n",
      "service": {
        "id": "bbc_radio_one"
      },
      "version": {
        "id": "m000w544"
      },
      "episode": {
        "id": "m000w545",
        "title": "Vick and Katie are in for Scott and Chris"
      },
      "brand": {
        "title": "Vick Hope and Katie Thistleton"
      },
      "masterbrand": {
        "id": "bbc_radio_one"
      },
      "published_time": {
        "start": "2021-05-20T12:00:00.000Z",
        "end": "2021-05-20T14:32:00.000Z"
      }
    },
    {
      "id": "p09g7f6p",
      "service": {
        "id": "bbc_radio_one"
      },
      "version": {
        "id": "m000w546"
      },
      "episode": {
        "id": "m000w547",
        "title": "Going Home Anthems"
      },
      "brand": {
        "title": "Nick Grimshaw"
      },
      "masterbrand": {
        "id": "bbc_radio_one"
      },
      "published_time": {
        "start": "2021-05-20T14:32:00.000Z",
        "end": "2021-05-20T16:45:00.000Z"
      }
    },
    {
      "id": "p09g7f6q",
      "service": {
        "id": "bbc_radio_one"
      },
      "version": {
        "id": "m000w548"
      },
      "episode": {
        "id": "m000w549",
        "title": "20/05/2021"
      },
      "brand": {
        "title": "Newsbeat"
      },
      "masterbrand": {
        "id": "bbc_radio_one"
      },
      "published_time": {
        "start": "2021-05-20T16:45:00.000Z",
        "end": "2021-05-20T17:00:00.000Z"
      }
    },
    {
      "id": "p09g7f6r",
      "service": {
        "id": "bbc_radio_one"
      },
      "version": {
        "id": "m000w54b"
      },
      "episode": {
        "id": "m000w54c",
        "title": "Krystal Klear Hottest Record"
      },
      "brand": {
        "title": "Radio 1's Future Sounds with Annie Mac"
      },
      "masterbrand": {
        "id": "bbc_radio_one"
      },
      "published_time": {
        "start": "2021-05-20T17:00:00.000Z",
        "end": "2021-05-20T19:00:00.000Z"
      }
    },
    {
      "id": "p09g7f6s",
      "service": {
        "id": "bbc_radio_one"
      },
      "version": {
        "id": "m000w54d"
      },
      "episode": {
        "id": "m000w54f",
        "title": "KURUPT FM TAKEOVER"
      },
      "brand": {
        "title": "Rickie, Melvin and Charlie"
      },
      "masterbrand": {
        "id": "bbc_radio_one"
      },
      "published_time": {
        "start": "2021-05-20T19:00:00.000Z",
        "end": "2021-05-20T20:30:00.000Z"
      }
    },
    {
      "id": "p09g7f6t",
      "service": {
        "id": "bbc_radio_one"
      },
      "version": {
        "id": "m000w54g"
      },
      "episode": {
        "id": "m000w54h",
        "title": "20/05/2021"
      },
      "brand": {
        "title": "Club Charlie"
      },
      "masterbrand": {
        "id": "bbc_radio_one"
      },
      "published_time": {
        "start": "2021-05-20T20:30:00.000Z",
        "end": "2021-05-20T21:00:00.000Z"
      }
    },
    {
      "id": "p09g7f6v",
      "service": {
        "id": "bbc_radio_one"
      },
      "version": {
        "id": "m000w54j"
      },
      "episode": {
        "id": "m000w54k",
        "title": "Good Health Good Wealth Next Wave"
      },
      "brand": {
        "title": "Radio 1's Indie Show with Jack Saunders"
      },
      "masterbrand": {
        "id": "bbc_radio_one"
      },
      "published_time": {
        "start": "2021-05-20T21:00:00.000Z",
        "end": "2021-05-20T23:00:00.000Z"
      }
    },
    {
      "id": "p09g7f6w",
      "service": {
        "id": "bbc_radio_one"
      },
      "version": {
        "id": "m000w54l"
      },
      "episode": {
        "id": "m000w54m",
        "title": "Patrick Guest Mix"
      },
      "brand": {
        "title": "Radio 1's Soundsystem with Jeremiah Asiamah"
      },
      "masterbrand": {
        "id": "bbc_radio_one"
      },
      "published_time": {
        "start": "2021-05-20T23:00:00.000Z",
        "end": "2021-05-21T01:00:00.000Z"
      }
    },
    {
      "id": "p09g7f6x",
      "service": {
        "id": "bbc_radio_one"
      },
      "version": {
        "id": "m000w54n"
      },
      "episode": {
        "id": "m000w54p",
        "title": "Response Guest Mix!"
      },
      "brand": {
        "title": "Radio 1's Drum & Bass Mix"
      },
      "masterbrand": {
        "id": "bbc_radio_one"
      },
      "published_time": {
        "start": "2021-05-21T01:00:00.000Z",
        "end": "2021-05-21T01:30:00.000Z"
      }
    },
    {
      "id": "p09d6sk0",
      "service": {
        "id": "bbc_radio_one"
      },
      "version": {
        "id": "m000s2w5"
      },
      "episode": {
        "id": "m000s2w6",
        "title": "Dossa & Locuzzed"
      },
      "brand": {
        "title": "Radio 1's Drum & Bass Mix"
      },
      "masterbrand": {
        "id": "bbc_radio_one"
      },
      "published_time": {
        "start": "2021-05-21T01:30:00.000Z",
        "end": "2021-05-21T02:00:00.000Z"
      }
    }
  ]
}