{
  "filters": {
    "serviceId": "bbc_radio_cambridge"
  },
  "service": {
    "id": "bbc_radio_cambridge",
    "name": "BBC Radio Cambridgeshire",
    "type": "Local Radio",
    "mediaType": "Audio",
    "scheduleUpdated": "2021-05-26T03:37:45.560Z"
  },
  "items": [
    {
      "id": "p09h4f7n",
      "service": {
        "id": "bbc_radio_cambridge"
      },
      "version": {
        "id": "p09h4f7f"
      },
      "episode": {
        "id": "p09h4f74",
        "title": "25/05/2021"
      },
      "brand": {
        "title": "Nick Risby"
      },
      "masterbrand": {
        "id": "bbc_local_radio"
      },
      "published_time": {
        "start": "2021-05-25T21:00:00.000Z",
        "end": "2021-05-26T00:00:00.000Z"
      }
    },
    {
      "id": "p09h4fg3",
      "service": {
        "id": "bbc_radio_cambridge"
      },
      "version": {
        "id": "p09gxjmp"
      },
      "episode": {
        "id": "p09gxjm7",
        "title": "26/05/2021"
      },
      "brand": {
        "title": "Dotun Adebayo with BBC Radio 5 live"
      },
      "masterbrand": {
        "id": "bbc_london"
      },
      "published_time": {
        "start": "2021-05-26T00:00:00.000Z",
        "end": "2021-05-26T04:00:00.000Z"
      }
    },
    {
      "id": "p09h4fg5",
      "service": {
        "id": "bbc_radio_cambridge"
      },
      "version": {
        "id": "p09gyd1y"
      },
      "episode": {
        "id": "p09gxjn3",
        "title": "26/05/2021"
      },
      "brand": {
        "title": "Jason Rosam"
      },
      "masterbrand": {
        "id": "bbc_london"
      },
      "published_time": {
        "start": "2021-05-26T04:00:00.000Z",
        "end": "2021-05-26T05:00:00.000Z"
      }
    },
    {
      "id": "p09h4fgh",
      "service": {
        "id": "bbc_radio_cambridge"
      },
      "version": {
        "id": "p09h4fgf"
      },
      "episode": {
        "id": "p09h4fg8",
        "title": "Dotty McLeod 26/05/2021"
      },
      "brand": {
        "title": "Breakfast on BBC Radio Cambridgeshire"
      },
      "masterbrand": {
        "id": "bbc_radio_cambridge"
      },
      "published_time": {
        "start": "2021-05-26T05:00:00.000Z",
        "end": "2021-05-26T09:00:00.000Z"
      }
    },
    {
      "id": "p09h4fj3",
      "service": {
        "id": "bbc_radio_cambridge"
      },
      "version": {
        "id": "p09h4fhd"
      },
      "episode": {
        "id": "p09h4fgx",
        "title": "Jeremy Sallis 26/05/2021"
      },
      "brand": {
        "title": "Mid-morning on BBC Radio Cambridgeshire"
      },
      "masterbrand": {
        "id": "bbc_radio_cambridge"
      },
      "published_time": {
        "start": "2021-05-26T09:00:00.000Z",
        "end": "2021-05-26T13:00:00.000Z"
      }
    },
    {
      "id": "p09h4fk2",
      "service": {
        "id": "bbc_radio_cambridge"
      },
      "version": {
        "id": "p09h4fjx"
      },
      "episode": {
        "id": "p09h4fjr",
        "title": "Chris Mann 26/05/2021"
      },
      "brand": {
        "title": "Afternoons on BBC Radio Cambridgeshire"
      },
      "masterbrand": {
        "id": "bbc_radio_cambridge"
      },
      "published_time": {
        "start": "2021-05-26T13:00:00.000Z",
        "end": "2021-05-26T17:00:00.000Z"
      }
    },
    {
      "id": "p09h4fk9",
      "service": {
        "id": "bbc_radio_cambridge"
      },
      "version": {
        "id": "p09h4fk7"
      },
      "episode": {
        "id": "p09h4fk4",
        "title": "26/05/2021"
      },
      "brand": {
        "title": "Upload on BBC Radio Cambridgeshire"
      },
      "masterbrand": {
        "id": "bbc_radio_cambridge"
      },
      "published_time": {
        "start": "2021-05-26T17:00:00.000Z",
        "end": "2021-05-26T18:00:00.000Z"
      }
    },
    {
      "id": "p09h4fkj",
      "service": {
        "id": "bbc_radio_cambridge"
      },
      "version": {
        "id": "p09h4fkd"
      },
      "episode": {
        "id": "p09h4fkb",
        "title": "Thordis Fridriksson 26/05/2021"
      },
      "brand": {
        "title": "Evenings on BBC Radio Cambridgeshire"
      },
      "masterbrand": {
        "id": "bbc_radio_cambridge"
      },
      "published_time": {
        "start": "2021-05-26T18:00:00.000Z",
        "end": "2021-05-26T21:00:00.000Z"
      }
    },
    {
      "id": "p09h4fkp",
      "service": {
        "id": "bbc_radio_cambridge"
      },
      "version": {
        "id": "p09h4fkm"
      },
      "episode": {
        "id": "p09h4fkk",
        "title": "26/05/2021"
      },
      "brand": {
        "title": "Nick Risby"
      },
      "masterbrand": {
        "id": "bbc_local_radio"
      },
      "published_time": {
        "start": "2021-05-26T21:00:00.000Z",
        "end": "2021-05-27T00:00:00.000Z"
      }
    }
  ]
}